{
    "picture1.jpg": {
        "person": 1,
        "cup": 1
    },
    "picture10.jpg": {},
    "picture100.jpg": {
        "person": 1
    },
    "picture11.jpg": {},
    "picture127.jpg": {
        "person": 2
    },
    "picture128.jpg": {
        "person": 4
    },
    "picture129.jpg": {
        "person": 8
    },
    "picture130.jpg": {},
    "picture131.jpg": {
        "person": 4
    },
    "picture133.jpg": {
        "person": 2
    },
    "picture136.jpg": {
        "car": 1
    },
    "picture137.jpg": {},
    "picture1374.jpg": {
        "person": 1
    },
    "picture1376.jpg": {
        "person": 3
    },
    "picture1423.jpg": {
        "person": 2
    },
    "picture1450.jpg": {
        "person": 2
    },
    "picture1491.jpg": {},
    "picture1494.jpg": {
        "person": 3
    },
    "picture1508.jpg": {},
    "picture1550.jpg": {
        "person": 1
    },
    "picture1567.jpg": {},
    "picture1588.jpg": {},
    "picture16.jpg": {},
    "picture1638.jpg": {},
    "picture1639.jpg": {
        "person": 4,
        "truck": 1
    },
    "picture166.jpg": {
        "person": 4
    },
    "picture167.jpg": {},
    "picture1681.jpg": {
        "person": 3
    },
    "picture1702.jpg": {
        "car": 1,
        "person": 3,
        "bicycle": 1
    },
    "picture1743.jpg": {
        "person": 6,
        "dog": 1
    },
    "picture1755.jpg": {
        "person": 3
    },
    "picture183.jpg": {
        "person": 1
    },
    "picture186.jpg": {},
    "picture187.jpg": {},
    "picture188.jpg": {},
    "picture189.jpg": {
        "person": 4,
        "sports ball": 1
    },
    "picture19.jpg": {
        "person": 3
    },
    "picture191.jpg": {
        "person": 3
    },
    "picture192.jpg": {
        "person": 2
    },
    "picture2.jpg": {},
    "picture204.jpg": {
        "horse": 1
    },
    "picture206.jpg": {
        "person": 5
    },
    "picture209.jpg": {},
    "picture215.jpg": {
        "person": 2
    },
    "picture216.jpg": {
        "train": 1
    },
    "picture22.jpg": {
        "person": 2
    },
    "picture224.jpg": {
        "person": 1
    },
    "picture23.jpg": {
        "person": 1
    },
    "picture24.jpg": {
        "person": 1
    },
    "picture25.jpg": {},
    "picture27.jpg": {
        "person": 1
    },
    "picture3.jpg": {},
    "picture30.jpg": {
        "person": 4
    },
    "picture306.jpg": {
        "person": 3
    },
    "picture32.jpg": {},
    "picture34.jpg": {
        "person": 4
    },
    "picture35.jpg": {},
    "picture36.jpg": {
        "person": 2
    },
    "picture38.jpg": {
        "person": 2
    },
    "picture39.jpg": {},
    "picture40.jpg": {
        "dog": 1
    },
    "picture41.jpg": {},
    "picture42.jpg": {},
    "picture43.jpg": {
        "person": 2
    },
    "picture44.jpg": {
        "person": 2,
        "potted plant": 2
    },
    "picture45.jpg": {},
    "picture46.jpg": {
        "dog": 2,
        "person": 1
    },
    "picture47.jpg": {
        "elephant": 1
    },
    "picture48.jpg": {
        "person": 1
    },
    "picture49.jpg": {
        "person": 2
    },
    "picture5.jpg": {
        "person": 1
    },
    "picture51.jpg": {
        "person": 2
    },
    "picture52.jpg": {
        "skateboard": 1
    },
    "picture53.jpg": {
        "horse": 1,
        "person": 1
    },
    "picture54.jpg": {
        "person": 4,
        "chair": 1
    },
    "picture55.jpg": {},
    "picture56.jpg": {
        "potted plant": 1
    },
    "picture57.jpg": {
        "person": 1
    },
    "picture59.jpg": {
        "person": 2
    },
    "picture6.jpg": {
        "bird": 1
    },
    "picture60.jpg": {
        "person": 2
    },
    "picture61.jpg": {
        "person": 1
    },
    "picture63.jpg": {
        "person": 2
    },
    "picture64.jpg": {},
    "picture7.jpg": {
        "person": 1
    },
    "picture79.jpg": {
        "person": 1
    },
    "picture8.jpg": {
        "person": 3
    },
    "picture80.jpg": {
        "person": 4
    },
    "picture83.jpg": {
        "person": 1
    },
    "picture86.jpg": {
        "person": 1
    },
    "picture88.jpg": {
        "person": 3
    },
    "picture90.jpg": {},
    "picture91.jpg": {
        "person": 2
    },
    "picture92.jpg": {
        "person": 1,
        "tie": 1
    },
    "picture93.jpg": {
        "person": 1
    },
    "picture94.jpg": {
        "person": 3
    },
    "picture95.jpg": {
        "person": 1
    },
    "picture96.jpg": {},
    "picture98.jpg": {
        "person": 1
    },
    "picture99.jpg": {
        "person": 1
    }
}